CHANGELOG.md
MANIFEST.in
README.md
setup.cfg
setup.py
versioneer.py
src/libreflow/__init__.py
src/libreflow.extensions.sk.export_psd_layers.egg-info/PKG-INFO
src/libreflow.extensions.sk.export_psd_layers.egg-info/SOURCES.txt
src/libreflow.extensions.sk.export_psd_layers.egg-info/dependency_links.txt
src/libreflow.extensions.sk.export_psd_layers.egg-info/requires.txt
src/libreflow.extensions.sk.export_psd_layers.egg-info/top_level.txt
src/libreflow/extensions/__init__.py
src/libreflow/extensions/sk/__init__.py
src/libreflow/extensions/sk/export_psd_layers/__init__.py
src/libreflow/extensions/sk/export_psd_layers/_version.py
src/libreflow/extensions/sk/export_psd_layers/scripts/PSD_crop_layers.jsx
src/libreflow/extensions/sk/export_psd_layers/scripts/__init__.py